scampy/Activation.py
scampy/Layer.py
scampy/Loss.py
scampy/Model.py
scampy/Optimizer.py
scampy/Util.py
scampy/__init__.py
scampy-1.0.3.dist-info/METADATA
scampy-1.0.3.dist-info/WHEEL
scampy-1.0.3.dist-info/licenses/LICENSE
scampy-1.0.3.dist-info/RECORD
